<?xml version="1.0"?>
<!--
 * Afptc View XML.
 * @category  Unilab
 * @package   Unilab_Afptc
 * @author    Kristian Claridad
-->


<page xmlns:xsi="http://www.w3.org/2001/XMLSchema-instance"
layout="admin-2columns-left" xsi:noNamespaceSchemaLocation="../../../../../../
../lib/internal/Magento/Framework/View/Layout/etc/page_configuration.xsd">
    <body>
        <referenceContainer name="left">
            <block class="Unilab\Afptc\Block\Adminhtml\Afptc\Edit\Tabs"
                name="afptc_edit_tab"/>
        </referenceContainer>
        <referenceContainer name="content">
            <block class="Unilab\Afptc\Block\Adminhtml\Afptc\Edit"
                name="afptc_edit_tab_main"/>
        </referenceContainer>
    </body>
</page>
